keepassxc_protocol/__init__.py
keepassxc_protocol/classes.py
keepassxc_protocol/classes_requests.py
keepassxc_protocol/classes_responses.py
keepassxc_protocol/connection_session.py
keepassxc_protocol/errors.py
keepassxc_protocol/kpx_protocol.py
keepassxc_protocol/winpipe.py
keepassxc_protocol-1.0.1.dist-info/LICENSE
keepassxc_protocol-1.0.1.dist-info/METADATA
keepassxc_protocol-1.0.1.dist-info/WHEEL
keepassxc_protocol-1.0.1.dist-info/RECORD
