Metadata-Version: 2.3
Name: keepassxc-protocol
Version: 1.0.1
Summary: 
License: Apache License
Keywords: keepassxc,keepassxc-protocol,keepassxc-python,password manager,keepassxc gui
Author: overgod
Author-email: vezonzzzzzz@gmail.com
Requires-Python: >=3.12,<4.0
Classifier: License :: Other/Proprietary License
Classifier: Programming Language :: Python :: 3
Classifier: Programming Language :: Python :: 3.12
Classifier: Programming Language :: Python :: 3.13
Requires-Dist: loguru (>=0.7.3,<1.0.0)
Requires-Dist: pydantic (>=2.11.9,<3.0.0)
Requires-Dist: pynacl (>=1.5.0,<2.0.0)
Requires-Dist: pywin32 (>=300,<400) ; sys_platform == "win32"
Requires-Dist: websockets (>=15.0)
Project-URL: Homepage, https://github.com/overgodofchaos/keepassxc-protocol
Project-URL: Repository, https://github.com/overgodofchaos/keepassxc-protocol.git
